{
  "name"          : "Wkhtmltox",
  "license"       : "MIT",
  "version"       : "0.0.3",
  "perl"          : "6.c",
  "description"   : "Convert HTML to PDF / Image using libwkhtmltox.",
  "test-depends"  : [
    "Test",
    "NativeHelpers::Blob"
  ],
  "auth"          : "github:azawawi",
  "authors"       : [ "Ahmad M. Zawawi" ],
  "provides"      : {
    "Wkhtmltox"         : "lib/Wkhtmltox.rakumod",
    "Wkhtmltox::Native" : "lib/Wkhtmltox/Native.rakumod",
    "Wkhtmltox::PDF"    : "lib/Wkhtmltox/PDF.rakumod",
    "Wkhtmltox::Image"  : "lib/Wkhtmltox/Image.rakumod"
  },
  "resources"     : [ ],
  "source-url"    : "git://github.com/azawawi/raku-wkhtmltox.git"
}
